resolve/import_timeline.py
shared/__init__.py
shared/ffmpeg_utils.py
shared/paths.py
shared/proxy.py
shared/vlm_client.py
shared/prompts/beat_alignment.txt
shared/prompts/best_in_burst.txt
shared/prompts/burst_similarity.txt
shared/prompts/photo_analysis.txt
shared/prompts/subject_sharpness.txt
shared/prompts/video_describe.txt
shared/prompts/video_trim.txt
tprs/__init__.py
tprs/cli.py
tprs/tprs.py
tprs/ui.py
tvas/__init__.py
tvas/_version.py
tvas/analysis.py
tvas/beats.py
tvas/ingestion.py
tvas/main.py
tvas/transcribe.py
tvas/trim.py
tvas/ui.py
tvas/vad.py
tvas/watcher.py
tvas-0.1.4.dist-info/METADATA
tvas-0.1.4.dist-info/WHEEL
tvas-0.1.4.dist-info/entry_points.txt
tvas-0.1.4.dist-info/top_level.txt
tvas-0.1.4.dist-info/RECORD
