Metadata-Version: 2.4
Name: tvas
Version: 0.1.4
Summary: Travel Vlog Automation System - Automate vlog ingestion, junk detection, and DaVinci Resolve import
License: MIT
Requires-Python: >=3.11
Requires-Dist: watchdog>=3.0.0
Requires-Dist: opencv-python>=4.8.0
Requires-Dist: mlx-vlm>=0.3.0
Requires-Dist: toga>=0.4.0
Requires-Dist: torchvision
Requires-Dist: opencc
Requires-Dist: mlx-whisper
Requires-Dist: silero-vad
Requires-Dist: onnxruntime
Provides-Extra: dev
Requires-Dist: pytest>=7.0.0; extra == "dev"
Requires-Dist: pytest-cov>=4.0.0; extra == "dev"
Provides-Extra: full
Requires-Dist: pytest>=7.0.0; extra == "full"
Requires-Dist: pytest-cov>=4.0.0; extra == "full"
